{
  "$schema": "https://ui.shadcn.com/schema/registry-item.json",
  "name": "divider",
  "title": "Sticker Divider",
  "description": "A semantic sticker separator for sections, metadata rows, and split panes.",
  "dependencies": [
    "class-variance-authority"
  ],
  "registryDependencies": [
    "utils"
  ],
  "files": [
    {
      "path": "src/components/ui/divider.tsx",
      "content": "import { cva, type VariantProps } from \"class-variance-authority\"\nimport * as React from \"react\"\n\nimport { cn } from \"@/lib/utils\"\n\n/**\n * Builds the divider root className from orientation and label alignment.\n */\nconst dividerVariants = cva(\"min-w-0 text-ink\", {\n  defaultVariants: {\n    align: \"center\",\n    orientation: \"horizontal\",\n  },\n  variants: {\n    align: {\n      center: \"justify-center\",\n      end: \"justify-end\",\n      start: \"justify-start\",\n    },\n    orientation: {\n      horizontal: \"flex w-full items-center\",\n      vertical: \"inline-flex min-h-8 flex-col items-center self-stretch\",\n    },\n  },\n})\n\nconst dividerLineVariants = cva(\"shrink-0\", {\n  compoundVariants: [\n    {\n      class: \"border-text-danger\",\n      tone: \"danger\",\n    },\n    {\n      class: \"border-ink\",\n      tone: \"default\",\n    },\n    {\n      class: \"border-text-info\",\n      tone: \"info\",\n    },\n    {\n      class: \"border-text-secondary\",\n      tone: \"secondary\",\n    },\n    {\n      class: \"border-text-success\",\n      tone: \"success\",\n    },\n    {\n      class: \"border-text-warning\",\n      tone: \"warning\",\n    },\n  ],\n  defaultVariants: {\n    orientation: \"horizontal\",\n    tone: \"default\",\n    variant: \"solid\",\n    weight: \"md\",\n  },\n  variants: {\n    orientation: {\n      horizontal: \"h-0 flex-1 border-t\",\n      vertical: \"w-0 flex-1 border-l\",\n    },\n    tone: {\n      danger: \"\",\n      default: \"\",\n      info: \"\",\n      secondary: \"\",\n      success: \"\",\n      warning: \"\",\n    },\n    variant: {\n      dashed: \"border-dashed\",\n      dotted: \"border-dotted\",\n      solid: \"border-solid\",\n    },\n    weight: {\n      lg: \"\",\n      md: \"\",\n      sm: \"\",\n    },\n  },\n})\n\ntype DividerOrientation = \"horizontal\" | \"vertical\"\ntype DividerTone =\n  | \"danger\"\n  | \"default\"\n  | \"info\"\n  | \"secondary\"\n  | \"success\"\n  | \"warning\"\n\n/**\n * Props for the sticker divider.\n * @remarks Inherits native div attributes and adds line orientation, tone, weight, and optional label content.\n */\ninterface DividerProps\n  extends\n    React.HTMLAttributes<HTMLDivElement>,\n    VariantProps<typeof dividerVariants>,\n    VariantProps<typeof dividerLineVariants> {\n  /**\n   * Aligns label content along a horizontal divider.\n   * @default \"center\"\n   */\n  align?: \"center\" | \"end\" | \"start\"\n  /**\n   * Hides the divider from assistive technology when it is purely decorative.\n   * @default true\n   */\n  decorative?: boolean\n  /**\n   * Controls divider direction.\n   * @default \"horizontal\"\n   */\n  orientation?: DividerOrientation\n  /**\n   * Controls semantic line color.\n   * @default \"default\"\n   */\n  tone?: DividerTone\n  /**\n   * Controls line style.\n   * @default \"solid\"\n   */\n  variant?: \"dashed\" | \"dotted\" | \"solid\"\n  /**\n   * Controls line thickness.\n   * @default \"md\"\n   */\n  weight?: \"lg\" | \"md\" | \"sm\"\n}\n\nconst dividerWeightClassNames = {\n  horizontal: {\n    lg: \"border-t-[3px]\",\n    md: \"border-t-2\",\n    sm: \"border-t\",\n  },\n  vertical: {\n    lg: \"border-l-[3px]\",\n    md: \"border-l-2\",\n    sm: \"border-l\",\n  },\n} satisfies Record<DividerOrientation, Record<\"lg\" | \"md\" | \"sm\", string>>\n\n/**\n * Sticker separator for sections, metadata rows, and split panes.\n */\nfunction Divider({\n  align = \"center\",\n  children,\n  className,\n  decorative = true,\n  orientation = \"horizontal\",\n  tone = \"default\",\n  variant = \"solid\",\n  weight = \"md\",\n  ...props\n}: DividerProps) {\n  const hasLabel = Boolean(children)\n  const accessibilityProps = decorative\n    ? { \"aria-hidden\": true }\n    : {\n        \"aria-orientation\": orientation,\n        role: \"separator\",\n      }\n  const lineClassName = cn(\n    dividerLineVariants({ orientation, tone, variant, weight }),\n    dividerWeightClassNames[orientation][weight],\n  )\n\n  return (\n    <div\n      className={cn(dividerVariants({ align, orientation }), className)}\n      data-align={align}\n      data-orientation={orientation}\n      data-slot=\"divider\"\n      data-tone={tone}\n      data-variant={variant}\n      data-weight={weight}\n      {...accessibilityProps}\n      {...props}\n    >\n      <span className={lineClassName} data-slot=\"divider-line\" />\n      {hasLabel ? (\n        <span\n          className={cn(\n            \"shrink-0 rounded-sticker-md bg-surface px-2.5 py-1 text-xs leading-none font-black text-ink\",\n            orientation === \"horizontal\" ? \"mx-3\" : \"my-2\",\n          )}\n          data-slot=\"divider-label\"\n        >\n          {children}\n        </span>\n      ) : null}\n      {hasLabel ? (\n        <span className={lineClassName} data-slot=\"divider-line\" />\n      ) : null}\n    </div>\n  )\n}\n\nexport { Divider, dividerVariants, type DividerProps }\n",
      "type": "registry:ui",
      "target": "@ui/divider.tsx"
    }
  ],
  "type": "registry:ui"
}